{"cameraMode":{"drawMode":0,"name":"Shaded","section":"Shading Mode"},"sceneLighting":false,"audioPlay":false,"sceneViewState":{"m_AlwaysRefresh":false,"showFog":true,"showSkybox":false,"showFlares":true,"showImageEffects":true,"showParticleSystems":true,"showVisualEffectGraphs":true,"m_FxEnabled":true},"in2DMode":false,"pivot":{"x":-6.51925802230835e-8,"y":3.0,"z":-2.529940128326416},"rotation":{"x":0.17753741145133973,"y":0.059002116322517398,"z":-0.010747849009931088,"w":0.9823120832443237},"size":0.3916636109352112,"orthographic":false}